{
    "goodId" : "3",
    "goodName" : "优美瞳妍妍两周抛6片装-棕色",
    "goodTitle" : "美瞳妍妍两周抛6片装-棕色",
    "originalPrice" : "130",
    "goodNum" : "100",
    "imgUrl" : "/images/1548160850791.jpg",
    "currentPrice" : "108",
    "goodIntro" : "亮眼网状设计，“智能曲弧设计”，操作方便，绝佳配适，两周设计更高价比，高效防紫外线保护，表现出众。",
    "goodType" : "海外购"
}
{
    "goodId" : "4",
    "goodName" : "强生安视优美瞳妍6片装-棕色",
    "goodTitle" : "强生安视优美瞳妍6片装-棕色",
    "originalPrice" : "130",
    "goodNum" : "100",
    "imgUrl" : "/images/1548160850791.jpg",
    "currentPrice" : "108",
    "goodIntro" : "亮眼网状设计，“智能曲弧设计”，操作方便，绝佳配适，两周设计更高价比，高效防紫外线保护，表现出众。",
    "goodType" : "海外购"
}{
    "goodId" : "5",
    "goodName" : "强生两周抛6片装-棕色",
    "goodTitle" : "强生两周抛6片装-棕色",
    "originalPrice" : "130",
    "goodNum" : "100",
    "imgUrl" : "/images/1548160850791.jpg",
    "currentPrice" : "108",
    "goodIntro" : "亮眼网状设计，“智能曲弧设计”，操作方便，绝佳配适，两周设计更高价比，高效防紫外线保护，表现出众。",
    "goodType" : "海外购"
}{
    "goodId" : "6",
    "goodName" : "强生安视两周抛6片装-棕色",
    "goodTitle" : "强生安视两周抛6片装-棕色",
    "originalPrice" : "130",
    "goodNum" : "100",
    "imgUrl" : "/images/1548160850791.jpg",
    "currentPrice" : "108",
    "goodIntro" : "亮眼网状设计，“智能曲弧设计”，操作方便，绝佳配适，两周设计更高价比，高效防紫外线保护，表现出众。",
    "goodType" : "海外购"
}{
    "goodId" : "7",
    "goodName" : "瞳妍妍两周抛6片装-棕色",
    "goodTitle" : "瞳妍妍两周抛6片装-棕色",
    "originalPrice" : "130",
    "goodNum" : "100",
    "imgUrl" : "/images/1548160850791.jpg",
    "currentPrice" : "108",
    "goodIntro" : "亮眼网状设计，“智能曲弧设计”，操作方便，绝佳配适，两周设计更高价比，高效防紫外线保护，表现出众。",
    "goodType" : "海外购"
}{
    "goodId" : "8",
    "goodName" : "强生安视优美瞳妍-棕色",
    "goodTitle" : "强生安视优美瞳妍-棕色",
    "originalPrice" : "130",
    "goodNum" : "100",
    "imgUrl" : "/images/1548160850791.jpg",
    "currentPrice" : "108",
    "goodIntro" : "亮眼网状设计，“智能曲弧设计”，操作方便，绝佳配适，两周设计更高价比，高效防紫外线保护，表现出众。",
    "goodType" : "海外购"
}{
    "goodId" : "9",
    "goodName" : "强生安视优美瞳妍-棕色",
    "goodTitle" : "强生安视优美瞳妍-棕色",
    "originalPrice" : "130",
    "goodNum" : "100",
    "imgUrl" : "/images/1548160850791.jpg",
    "currentPrice" : "108",
    "goodIntro" : "亮眼网状设计，“智能曲弧设计”，操作方便，绝佳配适，两周设计更高价比，高效防紫外线保护，表现出众。",
    "goodType" : "海外购"
}
{
    "goodId" : "10",
    "goodName" : "强生安视优美瞳妍-棕色",
    "goodTitle" : "强生安视优美瞳妍-棕色",
    "originalPrice" : "130",
    "goodNum" : "100",
    "imgUrl" : "/images/1548160850791.jpg",
    "currentPrice" : "108",
    "goodIntro" : "亮眼网状设计，“智能曲弧设计”，操作方便，绝佳配适，两周设计更高价比，高效防紫外线保护，表现出众。",
    "goodType" : "隐形眼镜"
}
{
    "goodId" : "11",
    "goodName" : "强生安视优美瞳妍-棕色",
    "goodTitle" : "强生安视优美瞳妍-棕色",
    "originalPrice" : "130",
    "goodNum" : "100",
    "imgUrl" : "/images/1548160850791.jpg",
    "currentPrice" : "108",
    "goodIntro" : "亮眼网状设计，“智能曲弧设计”，操作方便，绝佳配适，两周设计更高价比，高效防紫外线保护，表现出众。",
    "goodType" : "隐形眼镜"
}{
    "goodId" : "12",
    "goodName" : "强生安视优美瞳妍-棕色",
    "goodTitle" : "强生安视优美瞳妍-棕色",
    "originalPrice" : "130",
    "goodNum" : "100",
    "imgUrl" : "/images/1548160850791.jpg",
    "currentPrice" : "108",
    "goodIntro" : "亮眼网状设计，“智能曲弧设计”，操作方便，绝佳配适，两周设计更高价比，高效防紫外线保护，表现出众。",
    "goodType" : "隐形眼镜"
}{
    "goodId" : "13",
    "goodName" : "强生安视优美瞳妍-棕色",
    "goodTitle" : "强生安视优美瞳妍-棕色",
    "originalPrice" : "130",
    "goodNum" : "100",
    "imgUrl" : "/images/1548160850791.jpg",
    "currentPrice" : "108",
    "goodIntro" : "亮眼网状设计，“智能曲弧设计”，操作方便，绝佳配适，两周设计更高价比，高效防紫外线保护，表现出众。",
    "goodType" : "隐形眼镜"
}{
    "goodId" : "14",
    "goodName" : "强生安视优美瞳妍-棕色",
    "goodTitle" : "强生安视优美瞳妍-棕色",
    "originalPrice" : "130",
    "goodNum" : "100",
    "imgUrl" : "/images/1548160850791.jpg",
    "currentPrice" : "108",
    "goodIntro" : "亮眼网状设计，“智能曲弧设计”，操作方便，绝佳配适，两周设计更高价比，高效防紫外线保护，表现出众。",
    "goodType" : "隐形眼镜"
}{
    "goodId" : "15",
    "goodName" : "强生安视优美瞳妍-棕色",
    "goodTitle" : "强生安视优美瞳妍-棕色",
    "originalPrice" : "130",
    "goodNum" : "100",
    "imgUrl" : "/images/1548160850791.jpg",
    "currentPrice" : "108",
    "goodIntro" : "亮眼网状设计，“智能曲弧设计”，操作方便，绝佳配适，两周设计更高价比，高效防紫外线保护，表现出众。",
    "goodType" : "隐形眼镜"
}


{
    "goodId" : "16",
    "goodName" : "强生安视优美瞳妍-棕色",
    "goodTitle" : "强生安视优美瞳妍-棕色",
    "originalPrice" : "130",
    "goodNum" : "100",
    "imgUrl" : "/images/1548160850791.jpg",
    "currentPrice" : "108",
    "goodIntro" : "亮眼网状设计，“智能曲弧设计”，操作方便，绝佳配适，两周设计更高价比，高效防紫外线保护，表现出众。",
    "goodType" : "彩色眼镜"
}{
    "goodId" : "17",
    "goodName" : "强生安视优美瞳妍-棕色",
    "goodTitle" : "强生安视优美瞳妍-棕色",
    "originalPrice" : "130",
    "goodNum" : "100",
    "imgUrl" : "/images/1548160850791.jpg",
    "currentPrice" : "108",
    "goodIntro" : "亮眼网状设计，“智能曲弧设计”，操作方便，绝佳配适，两周设计更高价比，高效防紫外线保护，表现出众。",
    "goodType" : "彩色眼镜"
}{
    "goodId" : "18",
    "goodName" : "强生安视优美瞳妍-棕色",
    "goodTitle" : "强生安视优美瞳妍-棕色",
    "originalPrice" : "130",
    "goodNum" : "100",
    "imgUrl" : "/images/1548160850791.jpg",
    "currentPrice" : "108",
    "goodIntro" : "亮眼网状设计，“智能曲弧设计”，操作方便，绝佳配适，两周设计更高价比，高效防紫外线保护，表现出众。",
    "goodType" : "彩色眼镜"
}{
    "goodId" : "19",
    "goodName" : "强生安视优美瞳妍-棕色",
    "goodTitle" : "强生安视优美瞳妍-棕色",
    "originalPrice" : "130",
    "goodNum" : "100",
    "imgUrl" : "/images/1548160850791.jpg",
    "currentPrice" : "108",
    "goodIntro" : "亮眼网状设计，“智能曲弧设计”，操作方便，绝佳配适，两周设计更高价比，高效防紫外线保护，表现出众。",
    "goodType" : "彩色眼镜"
}{
    "goodId" : "20",
    "goodName" : "强生安视优美瞳妍-棕色",
    "goodTitle" : "强生安视优美瞳妍-棕色",
    "originalPrice" : "130",
    "goodNum" : "100",
    "imgUrl" : "/images/1548160850791.jpg",
    "currentPrice" : "108",
    "goodIntro" : "亮眼网状设计，“智能曲弧设计”，操作方便，绝佳配适，两周设计更高价比，高效防紫外线保护，表现出众。",
    "goodType" : "彩色眼镜"
}{
    "goodId" : "21",
    "goodName" : "强生安视优美瞳妍-棕色",
    "goodTitle" : "强生安视优美瞳妍-棕色",
    "originalPrice" : "130",
    "goodNum" : "100",
    "imgUrl" : "/images/1548160850791.jpg",
    "currentPrice" : "108",
    "goodIntro" : "亮眼网状设计，“智能曲弧设计”，操作方便，绝佳配适，两周设计更高价比，高效防紫外线保护，表现出众。",
    "goodType" : "彩色眼镜"
}{
    "goodId" : "22",
    "goodName" : "强生安视优美瞳妍-棕色",
    "goodTitle" : "强生安视优美瞳妍-棕色",
    "originalPrice" : "130",
    "goodNum" : "100",
    "imgUrl" : "/images/1548160850791.jpg",
    "currentPrice" : "108",
    "goodIntro" : "亮眼网状设计，“智能曲弧设计”，操作方便，绝佳配适，两周设计更高价比，高效防紫外线保护，表现出众。",
    "goodType" : "彩色眼镜"
}


{
    "goodId" : "23",
    "goodName" : "强生安视优美瞳妍-棕色",
    "goodTitle" : "强生安视优美瞳妍-棕色",
    "originalPrice" : "130",
    "goodNum" : "100",
    "imgUrl" : "/images/1548160850791.jpg",
    "currentPrice" : "108",
    "goodIntro" : "亮眼网状设计，“智能曲弧设计”，操作方便，绝佳配适，两周设计更高价比，高效防紫外线保护，表现出众。",
    "goodType" : "护理用品"
}
{
    "goodId" : "24",
    "goodName" : "强生安视优美瞳妍-棕色",
    "goodTitle" : "强生安视优美瞳妍-棕色",
    "originalPrice" : "130",
    "goodNum" : "100",
    "imgUrl" : "/images/1548160850791.jpg",
    "currentPrice" : "108",
    "goodIntro" : "亮眼网状设计，“智能曲弧设计”，操作方便，绝佳配适，两周设计更高价比，高效防紫外线保护，表现出众。",
    "goodType" : "护理用品"
}{
    "goodId" : "25",
    "goodName" : "强生安视优美瞳妍-棕色",
    "goodTitle" : "强生安视优美瞳妍-棕色",
    "originalPrice" : "130",
    "goodNum" : "100",
    "imgUrl" : "/images/1548160850791.jpg",
    "currentPrice" : "108",
    "goodIntro" : "亮眼网状设计，“智能曲弧设计”，操作方便，绝佳配适，两周设计更高价比，高效防紫外线保护，表现出众。",
    "goodType" : "护理用品"
}{
    "goodId" : "26",
    "goodName" : "强生安视优美瞳妍-棕色",
    "goodTitle" : "强生安视优美瞳妍-棕色",
    "originalPrice" : "130",
    "goodNum" : "100",
    "imgUrl" : "/images/1548160850791.jpg",
    "currentPrice" : "108",
    "goodIntro" : "亮眼网状设计，“智能曲弧设计”，操作方便，绝佳配适，两周设计更高价比，高效防紫外线保护，表现出众。",
    "goodType" : "护理用品"
}{
    "goodId" : "27",
    "goodName" : "强生安视优美瞳妍-棕色",
    "goodTitle" : "强生安视优美瞳妍-棕色",
    "originalPrice" : "130",
    "goodNum" : "100",
    "imgUrl" : "/images/1548160850791.jpg",
    "currentPrice" : "108",
    "goodIntro" : "亮眼网状设计，“智能曲弧设计”，操作方便，绝佳配适，两周设计更高价比，高效防紫外线保护，表现出众。",
    "goodType" : "护理用品"
}{
    "goodId" : "28",
    "goodName" : "强生安视优美瞳妍-棕色",
    "goodTitle" : "强生安视优美瞳妍-棕色",
    "originalPrice" : "130",
    "goodNum" : "100",
    "imgUrl" : "/images/1548160850791.jpg",
    "currentPrice" : "108",
    "goodIntro" : "亮眼网状设计，“智能曲弧设计”，操作方便，绝佳配适，两周设计更高价比，高效防紫外线保护，表现出众。",
    "goodType" : "护理用品"
}